<?xml version="1.0" encoding="utf-8" ?>
<dwsync>
<file name="dashboard.php" server="192.168.0.2//srv/www/htdocs/sandpit/" local="130644287519551582" remote="130644161650000000" Dst="0" />
<file name="filtro.php" server="192.168.0.2//srv/www/htdocs/sandpit/" local="130529824104594030" remote="130644161650000000" Dst="0" />
<file name="cartera_cobro_asignada.php" server="192.168.0.2//srv/www/htdocs/sandpit/" local="130647090925089122" remote="130646944020000000" Dst="0" />
<file name="listado_requerimiento_c.php" server="192.168.0.2//srv/www/htdocs/sandpit/" local="130647089793204239" remote="130646942890000000" Dst="0" />
<file name="cartera_cobro_asignada.php" server="192.168.0.2//srv/www/htdocs/testarossa/" local="130647090925089122" remote="130656412170000000" Dst="0" />
<file name="dashboard.php" server="192.168.0.2//srv/www/htdocs/testarossa/" local="130644287519551582" remote="130656412170000000" Dst="0" />
<file name="filtro.php" server="192.168.0.2//srv/www/htdocs/testarossa/" local="130529824104594030" remote="130656412170000000" Dst="0" />
<file name="listado_requerimiento_c.php" server="192.168.0.2//srv/www/htdocs/testarossa/" local="130647089793204239" remote="130656412170000000" Dst="0" />
<file name="cartera_cobro_asignada.php" server="192.168.0.6//var/www/html/sandbox/" local="130675326630648974" remote="130675453210000000" Dst="0" />
<file name="dashboard.php" server="192.168.0.6//var/www/html/sandbox/" local="130675331946355519" remote="130675453210000000" Dst="0" />
<file name="filtro.php" server="192.168.0.6//var/www/html/sandbox/" local="130529824104594030" remote="130675453210000000" Dst="0" />
<file name="listado_requerimiento_c.php" server="192.168.0.6//var/www/html/sandbox/" local="130673335261621189" remote="130675453210000000" Dst="0" />
</dwsync>